CHANGES.txt
LICENCE.txt
MANIFEST.in
README.md
VERSION.txt
ec2host.py
requirements.txt
setup.py
bin/ec2-rename
ec2_namer.egg-info/PKG-INFO
ec2_namer.egg-info/SOURCES.txt
ec2_namer.egg-info/dependency_links.txt
ec2_namer.egg-info/requires.txt
ec2_namer.egg-info/top_level.txt