Metadata-Version: 1.1
Name: ec2-namer
Version: 0.4.2
Summary: EC2 Namer - AWS EC2 host naming tool. Modifies hostname and public DNS routes based on EC2 tags.
Home-page: https://github.com/ronhanson/ec2-namer
Author: Ronan Delacroix
Author-email: ronan.delacroix@gmail.com
License: The MIT License (MIT)
